tensoraerospace/__init__.py
tensoraerospace/aerospacemodel/__init__.py
tensoraerospace/aerospacemodel/b747.py
tensoraerospace/aerospacemodel/base.py
tensoraerospace/aerospacemodel/cessna170.py
tensoraerospace/aerospacemodel/comsat.py
tensoraerospace/aerospacemodel/elv.py
tensoraerospace/aerospacemodel/f16/__init__.py
tensoraerospace/aerospacemodel/f16/linear/__init__.py
tensoraerospace/aerospacemodel/f16/linear/angular/__init__.py
tensoraerospace/aerospacemodel/f16/linear/angular/initial.py
tensoraerospace/aerospacemodel/f16/linear/angular/model.py
tensoraerospace/aerospacemodel/f16/linear/data/A.mat
tensoraerospace/aerospacemodel/f16/linear/data/B.mat
tensoraerospace/aerospacemodel/f16/linear/data/C.mat
tensoraerospace/aerospacemodel/f16/linear/data/D.mat
tensoraerospace/aerospacemodel/f16/linear/data/__init__.py
tensoraerospace/aerospacemodel/f16/linear/data/keySet_input.txt
tensoraerospace/aerospacemodel/f16/linear/data/keySet_output.txt
tensoraerospace/aerospacemodel/f16/linear/data/keySet_states.txt
tensoraerospace/aerospacemodel/f16/linear/longitudinal/__init__.py
tensoraerospace/aerospacemodel/f16/linear/longitudinal/initial.py
tensoraerospace/aerospacemodel/f16/linear/longitudinal/model.py
tensoraerospace/aerospacemodel/f16/nonlinear/__init__.py
tensoraerospace/aerospacemodel/f16/nonlinear/angular/__init__.py
tensoraerospace/aerospacemodel/f16/nonlinear/angular/inital.py
tensoraerospace/aerospacemodel/f16/nonlinear/angular/matlab_code/EnginePowerLevel.m
tensoraerospace/aerospacemodel/f16/nonlinear/angular/matlab_code/F16Control_vec2struct.m
tensoraerospace/aerospacemodel/f16/nonlinear/angular/matlab_code/F16ODE.m
tensoraerospace/aerospacemodel/f16/nonlinear/angular/matlab_code/F16State_vec2struct.m
tensoraerospace/aerospacemodel/f16/nonlinear/angular/matlab_code/GetCx.m
tensoraerospace/aerospacemodel/f16/nonlinear/angular/matlab_code/GetCy.m
tensoraerospace/aerospacemodel/f16/nonlinear/angular/matlab_code/GetCz.m
tensoraerospace-0.3.10.dist-info/METADATA
tensoraerospace-0.3.10.dist-info/WHEEL
tensoraerospace-0.3.10.dist-info/licenses/LICENSE
tensoraerospace-0.3.10.dist-info/RECORD
